zeroday/__init__.py
zeroday/__main__.py
zeroday/devops.py
zeroday-0.0.0.dist-info/METADATA
zeroday-0.0.0.dist-info/WHEEL
zeroday-0.0.0.dist-info/top_level.txt
zeroday-0.0.0.dist-info/RECORD
