Metadata-Version: 2.1
Name: zeroday
Version: 0.0.0
Summary: Zeroday | Comming Soon...
Home-page: UNKNOWN
Author: S41R4J
Author-email: <v1b7rc8eb@relay.firefox.com>
License: UNKNOWN
Platform: UNKNOWN
